<?xml version="1.0" encoding="utf-8"?>
<FurnitureCatalog xmlns:xsi="http://www.w3.org/2001/XMLSchema-instance" xmlns:xsd="http://www.w3.org/2001/XMLSchema">
  <Name>autumn Catalog</Name>
  <Season>Autumn</Season>
  <Items>
    <Chair>
      <Id>A01</Id>
      <Article>CH003</Article>
      <Brand>IKEA</Brand>
      <ModelName>Leaf</ModelName>
      <ImagePath>images/chair5.jpg</ImagePath>
      <HasBackSupport>true</HasBackSupport>
      <Legs>4</Legs>
    </Chair>
    <Table>
      <Id>A02</Id>
      <Article>TB003</Article>
      <Brand>RusticStyle</Brand>
      <ModelName>Maple</ModelName>
      <ImagePath>images/table5.jpg</ImagePath>
      <Area>90</Area>
      <IsFolding>false</IsFolding>
    </Table>
    <Sofa>
      <Id>A03</Id>
      <Article>SF003</Article>
      <Brand>RelaxCo</Brand>
      <ModelName>FallRest</ModelName>
      <ImagePath>images/sofa5.jpg</ImagePath>
      <Seats>3</Seats>
      <HasStorage>false</HasStorage>
    </Sofa>
    <Bed>
      <Id>A04</Id>
      <Article>BD003</Article>
      <Brand>Sleepy</Brand>
      <ModelName>AutumnDream</ModelName>
      <ImagePath>images/bed5.jpg</ImagePath>
      <Size>Double</Size>
      <HasHeadboard>false</HasHeadboard>
      <IsBunk>false</IsBunk>
    </Bed>
    <Stool>
      <Id>A05</Id>
      <Article>ST003</Article>
      <Brand>IKEA</Brand>
      <ModelName>Turnip</ModelName>
      <ImagePath>images/stool5.jpg</ImagePath>
      <HasBackSupport>false</HasBackSupport>
      <Legs>0</Legs>
      <IsSoft>true</IsSoft>
    </Stool>
    <Armchair>
      <Id>A06</Id>
      <Article>AR003</Article>
      <Brand>NobleSeat</Brand>
      <ModelName>Pumpkin</ModelName>
      <ImagePath>images/armchair5.jpg</ImagePath>
      <HasBackSupport>false</HasBackSupport>
      <Legs>0</Legs>
      <IsReclining>true</IsReclining>
    </Armchair>
  </Items>
</FurnitureCatalog>